ChengzhenMishangwoZhixinggeBuding/README.md
ChengzhenMishangwoZhixinggeBuding/__init__.py
ChengzhenMishangwoZhixinggeBuding/__main__.py
ChengzhenMishangwoZhixinggeBuding/file.epub
ChengzhenMishangwoZhixinggeBuding/index.html
ChengzhenMishangwoZhixinggeBuding/css/__init__.py
ChengzhenMishangwoZhixinggeBuding/css/annotations.css
ChengzhenMishangwoZhixinggeBuding/css/main.css
ChengzhenMishangwoZhixinggeBuding/css/normalize.css
ChengzhenMishangwoZhixinggeBuding/css/popup.css
ChengzhenMishangwoZhixinggeBuding/font/__init__.py
ChengzhenMishangwoZhixinggeBuding/font/fontello.eot
ChengzhenMishangwoZhixinggeBuding/font/fontello.svg
ChengzhenMishangwoZhixinggeBuding/font/fontello.ttf
ChengzhenMishangwoZhixinggeBuding/font/fontello.woff
ChengzhenMishangwoZhixinggeBuding/img/__init__.py
ChengzhenMishangwoZhixinggeBuding/img/annotator-glyph-sprite.png
ChengzhenMishangwoZhixinggeBuding/img/annotator-icon-sprite.png
ChengzhenMishangwoZhixinggeBuding/img/apple-touch-icon.png
ChengzhenMishangwoZhixinggeBuding/img/cancelfullscreen.png
ChengzhenMishangwoZhixinggeBuding/img/close.png
ChengzhenMishangwoZhixinggeBuding/img/fullscreen.png
ChengzhenMishangwoZhixinggeBuding/img/loader.gif
ChengzhenMishangwoZhixinggeBuding/img/menu-icon.png
ChengzhenMishangwoZhixinggeBuding/img/save.png
ChengzhenMishangwoZhixinggeBuding/img/saved.png
ChengzhenMishangwoZhixinggeBuding/img/settings-s.png
ChengzhenMishangwoZhixinggeBuding/img/settings.png
ChengzhenMishangwoZhixinggeBuding/img/star.png
ChengzhenMishangwoZhixinggeBuding/js/__init__.py
ChengzhenMishangwoZhixinggeBuding/js/epub.js
ChengzhenMishangwoZhixinggeBuding/js/epub.min.js
ChengzhenMishangwoZhixinggeBuding/js/epub.min.map
ChengzhenMishangwoZhixinggeBuding/js/hooks.min.js
ChengzhenMishangwoZhixinggeBuding/js/hooks.min.map
ChengzhenMishangwoZhixinggeBuding/js/reader.js
ChengzhenMishangwoZhixinggeBuding/js/reader.js.map
ChengzhenMishangwoZhixinggeBuding/js/reader.min.js
ChengzhenMishangwoZhixinggeBuding/js/reader.min.map
chengzhen_mishangwo_zhixingge_buding-2022.10.11.0.dist-info/METADATA
chengzhen_mishangwo_zhixingge_buding-2022.10.11.0.dist-info/WHEEL
chengzhen_mishangwo_zhixingge_buding-2022.10.11.0.dist-info/entry_points.txt
chengzhen_mishangwo_zhixingge_buding-2022.10.11.0.dist-info/top_level.txt
chengzhen_mishangwo_zhixingge_buding-2022.10.11.0.dist-info/RECORD
